findpi/__init__.py
findpi/__main__.py
findpi/__version__.py
findpi/findpi.py
findpi-1.2.2.dist-info/METADATA
findpi-1.2.2.dist-info/WHEEL
findpi-1.2.2.dist-info/entry_points.txt
findpi-1.2.2.dist-info/licenses/LICENSE
findpi-1.2.2.dist-info/RECORD
