Metadata-Version: 2.4
Name: findpi
Version: 1.2.2
Summary: Find Raspberry Pi devices on the network faster than nmap!
Project-URL: Homepage, https://github.com/james-see/findpi
Project-URL: Repository, https://github.com/james-see/findpi
Project-URL: Issues, https://github.com/james-see/findpi/issues
Author-email: James Campbell <james@jamescampbell.us>
License: MIT
License-File: LICENSE
Keywords: network-analysis,nmap,pi,raspberry,sbc
Classifier: Development Status :: 5 - Production/Stable
Classifier: Intended Audience :: Developers
Classifier: Intended Audience :: System Administrators
Classifier: License :: OSI Approved :: MIT License
Classifier: Operating System :: OS Independent
Classifier: Programming Language :: Python :: 3 :: Only
Classifier: Topic :: System :: Networking
Classifier: Topic :: System :: Systems Administration
Requires-Python: >=3.8
Requires-Dist: getmac>=0.9.4
Requires-Dist: psutil>=5.9.0
